{
    "type": "all.development.dr.production",
    "options": {
        "distributeOptions": {
            "gpii.config.deviceReporter.flowManager": {
                "record": "{flowManager}.solutionsRegistryDataSource",
                "target": "{that gpii.deviceReporter.live}.options.components.solutionsRegistryDataSource"
            }
        }
    },
    "mergeConfigs": [
        "%deviceReporter/configs/gpii.deviceReporter.config.production.json",
        "%flowManager/configs/gpii.flowManager.config.development.json",
        "%preferencesServer/configs/gpii.preferencesServer.config.development.json",
        "%flatMatchMaker/configs/gpii.flatMatchMaker.config.development.json",
        "%rawPreferencesServer/configs/gpii.rawPreferencesServer.config.development.json"
    ]
}
